MANIFEST.in
Readme.rst
setup.py
docker_remove/__init__.py
docker_remove/main.py
docker_remove.egg-info/PKG-INFO
docker_remove.egg-info/SOURCES.txt
docker_remove.egg-info/dependency_links.txt
docker_remove.egg-info/entry_points.txt
docker_remove.egg-info/not-zip-safe
docker_remove.egg-info/requires.txt
docker_remove.egg-info/top_level.txt
img/screenshot-1.png
img/screenshot-2.png
img/screenshot-3.png