Metadata-Version: 1.0
Name: docker-remove
Version: 1.0.5
Summary: Utility to easily remove Docker containers and Images through string matching
Home-page: https://github.com/monicagangwar/docker_remove
Author: Monica Gangwar
Author-email: monicagangwar10@gmail.com
License: GPL-3.0
Keywords: Docker
Platform: UNKNOWN
